MANIFEST.in
README.md
setup.cfg
setup.py
pyds9plugin/BasicFunctions.py
pyds9plugin/DS9Utils.py
pyds9plugin/Main.py
pyds9plugin/QuickLookPlugIn.ds9.ans
pyds9plugin/QuickLookPlugIn_DS9<8.2.ds9.ans
pyds9plugin/__init__.py
pyds9plugin/astrometry3.py
pyds9plugin/photometry.py
pyds9plugin.egg-info/PKG-INFO
pyds9plugin.egg-info/SOURCES.txt
pyds9plugin.egg-info/dependency_links.txt
pyds9plugin.egg-info/entry_points.txt
pyds9plugin.egg-info/requires.txt
pyds9plugin.egg-info/top_level.txt
pyds9plugin/Images/m33_hi.fits
pyds9plugin/Images/stack.fits
pyds9plugin/Images/stack18445218.fits
pyds9plugin/Images/stack18445542.fits
pyds9plugin/Images/stack18445868.fits
pyds9plugin/Images/stack18446197.fits
pyds9plugin/Images/stack18446524.fits
pyds9plugin/Images/stack18446850.fits
pyds9plugin/Images/stack18447179.fits
pyds9plugin/Images/stack18447503.fits
pyds9plugin/Images/stack18447826.fits
pyds9plugin/Images/stack18448156.fits
pyds9plugin/Images/stack18448483.fits
pyds9plugin/Macros/.DS_Store
pyds9plugin/Macros/Add_header_field.py
pyds9plugin/Macros/Autocorrelation.py
pyds9plugin/Macros/ColumnLineCorrelation.py
pyds9plugin/Macros/EMCCD_simulator.py
pyds9plugin/Macros/Interpolate_NaNs.py
pyds9plugin/Macros/Mask_cosmic_rays.py
pyds9plugin/Macros/My_first_macro.py
pyds9plugin/Macros/Replace_regions_by_value.py
pyds9plugin/Macros/Save_regions_as_table.py
pyds9plugin/Macros/bright_masking.py
pyds9plugin/Macros/edge_detection.py
pyds9plugin/Macros/Macros_Header_catalog/.DS_Store
pyds9plugin/Macros/Macros_Header_catalog/FIREBall.py
pyds9plugin/Macros/Macros_Header_catalog/basic_image_estimators.py
pyds9plugin/MaxiMask-1.1/.DS_Store
pyds9plugin/MaxiMask-1.1/LICENSE
pyds9plugin/MaxiMask-1.1/README.md
pyds9plugin/MaxiMask-1.1/classes.flags
pyds9plugin/MaxiMask-1.1/classes.priors
pyds9plugin/MaxiMask-1.1/classes.thresh
pyds9plugin/MaxiMask-1.1/logo.png
pyds9plugin/MaxiMask-1.1/maximask.py
pyds9plugin/MaxiMask-1.1/maxitrack.py
pyds9plugin/MaxiMask-1.1/test_inp.fits.fz
pyds9plugin/MaxiMask-1.1/test_out.fits.fz
pyds9plugin/MaxiMask-1.1/utils.py
pyds9plugin/MaxiMask-1.1/model/.DS_Store
pyds9plugin/MaxiMask-1.1/model/model-150000.data-00000-of-00001
pyds9plugin/MaxiMask-1.1/model/model-150000.index
