Metadata-Version: 1.2
Name: pyds9plugin
Version: 3.1.dev7
Summary: DS9 Quick-Look plug-in
Home-page: https://people.lam.fr/picouet.vincent/index.html
Author: Vincent Picouet
Author-email: vincent.picouet@lam.fr
Maintainer: Vincent Picouet
License: CeCILL-B
Platform: Linux
Platform: Mac OS-X
Platform: Unix
Requires-Python: >3.5.2
